{
    "keep": {
        "days": true,
        "amount": 14
    },
    "auditLog": "logs\\server\\daily\\.66f9134d6120569f739e98c9ffd0130985b9b2a5-audit.json",
    "files": [
        {
            "date": 1702535306596,
            "name": "logs\\server\\daily\\2023-12-14.log",
            "hash": "378ab7fc2bbc1550ea5a0d3822a4b28749751a29e05b5a2ebb4b43f37e9e1665"
        },
        {
            "date": 1702618943809,
            "name": "logs\\server\\daily\\2023-12-15.log",
            "hash": "7cd6a70ac18d405628bca63c20b21bb6caee0246e0e0294a66906d5516de68c6"
        },
        {
            "date": 1702706663138,
            "name": "logs\\server\\daily\\2023-12-16.log",
            "hash": "2e671fd81f9be802a71e9c67744ef785e7314a0538f1df94d5409ee836f5984e"
        },
        {
            "date": 1702820155350,
            "name": "logs\\server\\daily\\2023-12-17.log",
            "hash": "36c43d5789895e8f9cf16b9e60f8cf0cb712ffee1b5218c95669ed08b490de0d"
        }
    ],
    "hashType": "sha256"
}